{"is_source_file": true, "format": "JavaScript", "description": "Test setup file for configuring jest-dom custom matchers for testing-library in React project.", "external_files": ["@testing-library/jest-dom"], "external_methods": [], "published": [], "classes": [], "methods": [], "calls": ["import '@testing-library/jest-dom'"], "search-terms": ["jest-dom", "setupTests", "react testing-library", "custom matchers", "testing"], "state": 2, "file_id": 4, "knowledge_revision": 18, "git_revision": "4befbae8eaa058f32f69fa1e89a898399d096a7b", "ctags": [], "hash": "1a77571e1a8cf36018a41bcedf60db75", "format-version": 4, "code-base-name": "frontend_react", "filename": "frontend_react/src/setupTests.js", "revision_history": [{"18": "4befbae8eaa058f32f69fa1e89a898399d096a7b"}]}